Workbook

Sheet Read Me
A1: Nestlé India Ltd — Financial Analysis Workbook (FY2015–FY2026)
A3: Prepared by: Hiteshi | Business Analytics Project
A4: Data source: Screener.in (standalone financials, sourced from Nestlé India's audited annual reports / BSE filings), retrieved July 2026.
A5: Figures are in ₹ Crores unless stated otherwise.
A7: IMPORTANT NOTE ON FY2024:
A8: Nestlé India changed its financial year-end from 31 December to 31 March in 2024 (aligning with the standard Indian statutory fiscal year).
A9: As a result, the FY2024 column below (labelled FY2024_15M) covers a transition period of 15 months (Jan 2023–Mar 2024), not a standard 12-month year.
A10: This makes FY2024 Sales, Profit, and cash flow figures NOT directly comparable to other years on a like-for-like basis — a key analytical
A11: caveat similar to the FY21 GSK Consumer Healthcare amalgamation anomaly seen in HUL's numbers. This is called out explicitly in the Ratios
A12: sheet and in the accompanying report.
A14: Sheet guide:
A15: 1. P&L — Standalone Profit & Loss statement, FY2015–FY2026 (input data)
... A21: Color legend: Blue text = hardcoded input (sourced data) | Black text = formula | Green text = cross-sheet link

Sheet P&L
A1: Nestlé India — P&L (₹ Crores, Standalone)
A3: Line Item | B3: FY2015 | C3: FY2016 | D3: FY2017 | E3: FY2018 | F3: FY2019 | G3: FY2020 | H3: FY2021 | I3: FY2022 | J3: FY2023 | K3: FY2024 (15M) | L3: FY2025 | M3: FY2026
A4: Sales | B4: 8175 | C4: 9141 | D4: 10010 | E4: 11292 | F4: 12369 | G4: 13350 | H4: 14741 | I4: 16897 | J4: 19126 | K4: 24394 | L4: 20202 | M4: 23155
A5: Expenses | B5: 6620 | C5: 7292 | D5: 7913 | E5: 8675 | F5: 9443 | G5: 10149 | H5: 11178 | I5: 13191 | J5: 14655 | K5: 18551 | L5: 15430 | M5: 17848
A6: Operating Profit | B6: 1555 | C6: 1850 | D6: 2097 | E6: 2618 | F6: 2926 | G6: 3202 | H6: 3562 | I6: 3706 | J6: 4471 | K6: 5843 | L6: 4771 | M6: 5307
A7: OPM % | B7: 19 | C7: 20 | D7: 21 | E7: 23 | F7: 24 | G7: 24 | H7: 24 | I7: 22 | J7: 23 | K7: 24 | L7: 24 | M7: 23
A8: Other Income | B8: -391 | C8: 140 | D8: 177 | E8: 259 | F8: 247 | G8: 146 | H8: -112 | I8: 107 | J8: 116 | K8: 159 | L8: 352 | M8: 160
A9: Interest | B9: 3 | C9: 91 | D9: 92 | E9: 112 | F9: 129 | G9: 164 | H9: 202 | I9: 155 | J9: 119 | K9: 145 | L9: 136 | M9: 158
A10: Depreciation | B10: 347 | C10: 354 | D10: 342 | E10: 336 | F10: 370 | G10: 370 | H10: 391 | I10: 403 | J10: 429 | K10: 568 | L10: 540 | M10: 699
A11: PBT | B11: 814 | C11: 1545 | D11: 1839 | E11: 2429 | F11: 2673 | G11: 2813 | H11: 2857 | I11: 3256 | J11: 4038 | K11: 5289 | L11: 4447 | M11: 4610
A12: Tax % | B12: 31 | C12: 35 | D12: 33 | E12: 34 | F12: 26 | G12: 26 | H12: 26 | I12: 27 | J12: 26 | K12: 26 | L12: 25 | M12: 23
A13: Net Profit | B13: 563 | C13: 1001 | D13: 1225 | E13: 1607 | F13: 1968 | G13: 2082 | H13: 2118 | I13: 2391 | J13: 2999 | K13: 3933 | L13: 3314 | M13: 3545
A14: EPS | B14: 2.92 | C14: 5.19 | D14: 6.35 | E14: 8.33 | F14: 10.21 | G14: 10.8 | H14: 10.99 | I14: 12.4 | J14: 15.55 | K14: 20.4 | L14: 17.19 | M14: 18.38
A15: Dividend Payout % | B15: 83 | C15: 61 | D15: 68 | E15: 69 | F15: 168 | G15: 93 | H15: 91 | I15: 89 | J15: 56 | K15: 79 | L15: 79 | M15: 65
A17: Source: Screener.in, standalone figures from Nestlé India audited financial statements. FY2024 column = 15-month transition period (Jan'23–Mar'24) due to year-end change.

Sheet Balance Sheet
A1: Nestlé India — Balance Sheet (₹ Crores, Standalone)
A3: Line Item | B3: FY2015 | C3: FY2016 | D3: FY2017 | E3: FY2018 | F3: FY2019 | G3: FY2020 | H3: FY2021 | I3: FY2022 | J3: FY2023 | K3: FY2024 (15M) | L3: FY2025 | M3: FY2026
A4: Equity Capital | B4: 96 | C4: 96 | D4: 96 | E4: 96 | F4: 96 | G4: 96 | H4: 96 | I4: 96 | J4: 96 | K4: 96 | L4: 96 | M4: 193
A5: Reserves | B5: 2721 | C5: 3186 | D5: 3324 | E5: 3577 | F5: 1822 | G5: 1923 | H5: 1850 | I5: 2363 | J5: 2363 | K5: 3244 | L5: 4021 | M5: 5116
A6: Borrowings | B6: 18 | C6: 33 | D6: 35 | E6: 35 | F6: 189 | G6: 147 | H6: 266 | I6: 271 | J6: 271 | K6: 345 | L6: 1167 | M6: 444
A7: Other Liabilities | B7: 3251 | C7: 3495 | D7: 3907 | E7: 4379 | F7: 5065 | G7: 5733 | H7: 6021 | I7: 6249 | J7: 6249 | K7: 6838 | L7: 7040 | M7: 7604
A8: Total Liabilities | B8: 6086 | C8: 6810 | D8: 7363 | E8: 8088 | F8: 7173 | G8: 7900 | H8: 8234 | I8: 8979 | J8: 8979 | K8: 10523 | L8: 12324 | M8: 13357
A9: Fixed Assets | B9: 2898 | C9: 2730 | D9: 2616 | E9: 2401 | F9: 2341 | G9: 2179 | H9: 2995 | I9: 3044 | J9: 3044 | K9: 3460 | L9: 5474 | M9: 6290
A10: CWIP | B10: 231 | C10: 188 | D10: 94 | E10: 105 | F10: 143 | G10: 639 | H10: 246 | I10: 358 | J10: 358 | K10: 1742 | L10: 1173 | M10: 507
A11: Investments | B11: 1325 | C11: 1756 | D11: 1979 | E11: 2658 | F11: 1751 | G11: 1464 | H11: 774 | I11: 778 | J11: 778 | K11: 464 | L11: 706 | M11: 706
A12: Other Assets | B12: 1633 | C12: 2136 | D12: 2673 | E12: 2924 | F12: 2937 | G12: 3618 | H12: 4219 | I12: 4799 | J12: 4799 | K12: 4857 | L12: 4972 | M12: 5854
A13: Total Assets | B13: 6086 | C13: 6810 | D13: 7363 | E13: 8088 | F13: 7173 | G13: 7900 | H13: 8234 | I13: 8979 | J13: 8979 | K13: 10523 | L13: 12324 | M13: 13357
A15: Source: Screener.in, standalone figures from Nestlé India audited financial statements. FY2024 column = 15-month transition period (Jan'23–Mar'24) due to year-end change.

Sheet Cash Flow
A1: Nestlé India — Cash Flow (₹ Crores, Standalone)
A3: Line Item | B3: FY2015 | C3: FY2016 | D3: FY2017 | E3: FY2018 | F3: FY2019 | G3: FY2020 | H3: FY2021 | I3: FY2022 | J3: FY2023 | K3: FY2024 (15M) | L3: FY2025 | M3: FY2026
A4: CFO | B4: 1098 | C4: 1466 | D4: 1818 | E4: 2052 | F4: 2295 | G4: 2454 | H4: 2236 | I4: 2737 | J4: 3392 | K4: 4175 | L4: 2935 | M4: 5048
A5: CFI | B5: -70 | C5: -126 | D5: -131 | E5: -52 | F5: 83 | G5: -321 | H5: -1920 | I5: -392 | J5: -927 | K5: -1237 | L5: -1811 | M5: -624
A6: CFF | B6: -498 | C6: -666 | D6: -997 | E6: -1317 | F6: -3602 | G6: -1956 | H6: -2020 | I6: -2123 | J6: -2436 | K6: -3135 | L6: -1846 | M6: -3179
A7: Net Cash Flow | B7: 529 | C7: 674 | D7: 691 | E7: 683 | F7: -1223 | G7: 177 | H7: -1704 | I7: 223 | J7: 29 | K7: -198 | L7: -723 | M7: 1244
A8: FCF | B8: 949 | C8: 1353 | D8: 1622 | E8: 1890 | F8: 2143 | G8: 1980 | H8: 1505 | I8: 2197 | J8: 2028 | K8: 2296 | L8: 930 | M8: 4221
A9: CFO OP % | B9: 93 | C9: 106 | D9: 116 | E9: 112 | F9: 101 | G9: 99 | H9: 83 | I9: 97 | J9: 100 | K9: 94 | L9: 82 | M9: 115
A11: Source: Screener.in, standalone figures from Nestlé India audited financial statements. FY2024 column = 15-month transition period (Jan'23–Mar'24) due to year-end change.

Sheet Ratios Given
A1: Nestlé India — Ratios Given (₹ Crores, Standalone)
A3: Line Item | B3: FY2015 | C3: FY2016 | D3: FY2017 | E3: FY2018 | F3: FY2019 | G3: FY2020 | H3: FY2021 | I3: FY2022 | J3: FY2023 | K3: FY2024 (15M) | L3: FY2025 | M3: FY2026
A4: Debtor Days | B4: 4 | C4: 4 | D4: 3 | E4: 4 | F4: 4 | G4: 5 | H4: 4 | I4: 4 | J4: 4 | K4: 4 | L4: 7 | M4: 5
A5: Inventory Days | B5: 103 | C5: 107 | D5: 91 | E5: 92 | F5: 107 | G5: 107 | H5: 111 | I5: 110 | J5: 83 | K5: 83 | L5: 139 | M5: 105
A6: Days Payable | B6: 94 | C6: 91 | D6: 99 | E6: 118 | F6: 124 | G6: 115 | H6: 122 | I6: 121 | J6: 92 | K6: 112 | L6: 128 | M6: 129
A7: Cash Conversion Cycle | B7: 12 | C7: 20 | D7: -5 | E7: -22 | F7: -14 | G7: -3 | H7: -7 | I7: -7 | J7: -5 | K7: -24 | L7: 18 | M7: -19
A8: Working Capital Days | B8: -21 | C8: -10 | D8: -15 | E8: -21 | F8: -20 | G8: -22 | H8: -20 | I8: -16 | J8: -10 | K8: -19 | L8: -19 | M8: -24
A9: ROCE % | B9: 46 | C9: 54 | D9: 57 | E9: 71 | F9: 96 | G9: 139 | H9: 150 | I9: 138 | J9: 153 | K9: 169 | L9: 96 | M9: 84
A11: Source: Screener.in, standalone figures from Nestlé India audited financial statements. FY2024 column = 15-month transition period (Jan'23–Mar'24) due to year-end change.

Sheet Ratios
A1: Nestlé India — Computed Ratios (formulas link to P&L / Balance Sheet / Ratios Given)
A3: Ratio | B3: FY2015 | C3: FY2016 | D3: FY2017 | E3: FY2018 | F3: FY2019 | G3: FY2020 | H3: FY2021 | I3: FY2022 | J3: FY2023 | K3: FY2024 (15M) | L3: FY2025 | M3: FY2026
A4: Net Profit Margin % | B4: ='P&L'!B13/'P&L'!B4*100 -> 6.8868502 | C4: ='P&L'!C13/'P&L'!C4*100 -> 10.950662 | D4: ='P&L'!D13/'P&L'!D4*100 -> 12.237762 | E4: ='P&L'!E13/'P&L'!E4*100 -> 14.231314 | F4: ='P&L'!F13/'P&L'!F4*100 -> 15.910745 | G4: ='P&L'!G13/'P&L'!G4*100 -> 15.595506 | H4: ='P&L'!H13/'P&L'!H4*100 -> 14.368089 | I4: ='P&L'!I13/'P&L'!I4*100 -> 14.150441 | ... M4: ='P&L'!M13/'P&L'!M4*100 -> 15.309868
A5: Operating Margin % (recomputed) | B5: ='P&L'!B6/'P&L'!B4*100 -> 19.021407 | C5: ='P&L'!C6/'P&L'!C4*100 -> 20.238486 | D5: ='P&L'!D6/'P&L'!D4*100 -> 20.949051 | E5: ='P&L'!E6/'P&L'!E4*100 -> 23.184555 | F5: ='P&L'!F6/'P&L'!F4*100 -> 23.655914 | G5: ='P&L'!G6/'P&L'!G4*100 -> 23.985019 | H5: ='P&L'!H6/'P&L'!H4*100 -> 24.163897 | I5: ='P&L'!I6/'P&L'!I4*100 -> 21.932887 | ... M5: ='P&L'!M6/'P&L'!M4*100 -> 22.919456
A6: Return on Equity % (computed) | B6: ='P&L'!B13/('Balance Sheet'!B4+'Balance Sheet'!B5)*100 -> 19.9858 | C6: ='P&L'!C13/('Balance Sheet'!C4+'Balance Sheet'!C5)*100 -> 30.499695 | D6: ='P&L'!D13/('Balance Sheet'!D4+'Balance Sheet'!D5)*100 -> 35.818713 | E6: ='P&L'!E13/('Balance Sheet'!E4+'Balance Sheet'!E5)*100 -> 43.751702 | F6: ='P&L'!F13/('Balance Sheet'!F4+'Balance Sheet'!F5)*100 -> 102.60688 | G6: ='P&L'!G13/('Balance Sheet'!G4+'Balance Sheet'!G5)*100 -> 103.12036 | H6: ='P&L'!H13/('Balance Sheet'!H4+'Balance Sheet'!H5)*100 -> 108.83864 | I6: ='P&L'!I13/('Balance Sheet'!I4+'Balance Sheet'!I5)*100 -> 97.234648 | ... M6: ='P&L'!M13/('Balance Sheet'!M4+'Balance Sheet'!M5)*100 -> 66.773404
A7: ROCE % (as reported) | B7: ='Ratios Given'!B9 -> 46 | C7: ='Ratios Given'!C9 -> 54 | D7: ='Ratios Given'!D9 -> 57 | E7: ='Ratios Given'!E9 -> 71 | F7: ='Ratios Given'!F9 -> 96 | G7: ='Ratios Given'!G9 -> 139 | H7: ='Ratios Given'!H9 -> 150 | I7: ='Ratios Given'!I9 -> 138 | ... M7: ='Ratios Given'!M9 -> 84
A8: Debt-to-Equity (x) | B8: ='Balance Sheet'!B6/('Balance Sheet'!B4+'Balance Sheet'!B5) -> 0.0063897764 | C8: ='Balance Sheet'!C6/('Balance Sheet'!C4+'Balance Sheet'!C5) -> 0.010054845 | D8: ='Balance Sheet'!D6/('Balance Sheet'!D4+'Balance Sheet'!D5) -> 0.010233918 | E8: ='Balance Sheet'!E6/('Balance Sheet'!E4+'Balance Sheet'!E5) -> 0.0095289954 | F8: ='Balance Sheet'!F6/('Balance Sheet'!F4+'Balance Sheet'!F5) -> 0.098540146 | G8: ='Balance Sheet'!G6/('Balance Sheet'!G4+'Balance Sheet'!G5) -> 0.072808321 | H8: ='Balance Sheet'!H6/('Balance Sheet'!H4+'Balance Sheet'!H5) -> 0.13669065 | I8: ='Balance Sheet'!I6/('Balance Sheet'!I4+'Balance Sheet'!I5) -> 0.1102074 | ... M8: ='Balance Sheet'!M6/('Balance Sheet'!M4+'Balance Sheet'!M5) -> 0.083631569
A9: Interest Coverage Ratio (x) | B9: =('P&L'!B11+'P&L'!B9)/'P&L'!B9 -> 272.33333 | C9: =('P&L'!C11+'P&L'!C9)/'P&L'!C9 -> 17.978022 | D9: =('P&L'!D11+'P&L'!D9)/'P&L'!D9 -> 20.98913 | E9: =('P&L'!E11+'P&L'!E9)/'P&L'!E9 -> 22.6875 | F9: =('P&L'!F11+'P&L'!F9)/'P&L'!F9 -> 21.72093 | G9: =('P&L'!G11+'P&L'!G9)/'P&L'!G9 -> 18.152439 | H9: =('P&L'!H11+'P&L'!H9)/'P&L'!H9 -> 15.143564 | I9: =('P&L'!I11+'P&L'!I9)/'P&L'!I9 -> 22.006452 | ... M9: =('P&L'!M11+'P&L'!M9)/'P&L'!M9 -> 30.177215
A10: Asset Turnover Ratio (x) | B10: ='P&L'!B4/'Balance Sheet'!B13 -> 1.3432468 | C10: ='P&L'!C4/'Balance Sheet'!C13 -> 1.3422907 | D10: ='P&L'!D4/'Balance Sheet'!D13 -> 1.3595002 | E10: ='P&L'!E4/'Balance Sheet'!E13 -> 1.3961424 | F10: ='P&L'!F4/'Balance Sheet'!F13 -> 1.7243831 | G10: ='P&L'!G4/'Balance Sheet'!G13 -> 1.6898734 | H10: ='P&L'!H4/'Balance Sheet'!H13 -> 1.7902599 | I10: ='P&L'!I4/'Balance Sheet'!I13 -> 1.8818354 | ... M10: ='P&L'!M4/'Balance Sheet'!M13 -> 1.733548
A11: EPS Growth YoY % | B11: n/a | C11: =('P&L'!C14-'P&L'!B14)/'P&L'!B14*100 -> 77.739726 | D11: =('P&L'!D14-'P&L'!C14)/'P&L'!C14*100 -> 22.350674 | E11: =('P&L'!E14-'P&L'!D14)/'P&L'!D14*100 -> 31.181102 | F11: =('P&L'!F14-'P&L'!E14)/'P&L'!E14*100 -> 22.569028 | G11: =('P&L'!G14-'P&L'!F14)/'P&L'!F14*100 -> 5.7786484 | H11: =('P&L'!H14-'P&L'!G14)/'P&L'!G14*100 -> 1.7592593 | I11: =('P&L'!I14-'P&L'!H14)/'P&L'!H14*100 -> 12.829845 | J11: =('P&L'!J14-'P&L'!I14)/'P&L'!I14*100 -> 25.403226 | ... M11: =('P&L'!M14-'P&L'!L14)/'P&L'!L14*100 -> 6.9226294
A12: Free Cash Flow Margin % | B12: ='Cash Flow'!B8/'P&L'!B4*100 -> 11.608563 | C12: ='Cash Flow'!C8/'P&L'!C4*100 -> 14.801444 | D12: ='Cash Flow'!D8/'P&L'!D4*100 -> 16.203796 | E12: ='Cash Flow'!E8/'P&L'!E4*100 -> 16.737513 | F12: ='Cash Flow'!F8/'P&L'!F4*100 -> 17.325572 | G12: ='Cash Flow'!G8/'P&L'!G4*100 -> 14.831461 | H12: ='Cash Flow'!H8/'P&L'!H4*100 -> 10.209619 | I12: ='Cash Flow'!I8/'P&L'!I4*100 -> 13.002308 | ... M12: ='Cash Flow'!M8/'P&L'!M4*100 -> 18.229324
A13: Cash Conversion Cycle (days) | B13: ='Ratios Given'!B7 -> 12 | C13: ='Ratios Given'!C7 -> 20 | D13: ='Ratios Given'!D7 -> -5 | E13: ='Ratios Given'!E7 -> -22 | F13: ='Ratios Given'!F7 -> -14 | G13: ='Ratios Given'!G7 -> -3 | H13: ='Ratios Given'!H7 -> -7 | I13: ='Ratios Given'!I7 -> -7 | ... M13: ='Ratios Given'!M7 -> -19
A15: Caution: FY2024 (15-month transition period) distorts YoY growth ratios — treat FY2024 comparisons with care; FY2025 vs FY2023 (both ~12-month periods) is a cleaner comparison.

Sheet Dashboard
B2: Nestlé India Ltd — Financial Performance Dashboard (FY2015–FY2026)
B3: Standalone figures, ₹ Crores. FY2024 = 15-month transition period (year-end change from Dec to Mar). Source: Screener.in
B40: Key observations:
B41: • Revenue grew from ₹8,175 Cr (FY15) to ₹23,155 Cr (FY26) — a ~11% CAGR, but FY24's 15-month period inflates the apparent jump.
B42: • Operating margin expanded from 19% (FY15) to a peak of ~26% in strong quarters, settling around 23-24% — steady, disciplined cost control.
B43: • ROCE peaked at 169% in FY24 (15-month, capex-light) then fell to 84% by FY26 as the company entered a capex supercycle (Fixed Assets nearly doubled FY24→FY26).
B44: • Borrowings spiked to ₹1,167 Cr in FY25 before being paid down to ₹444 Cr in FY26 — a short-term debt-funded capex bridge, later refinanced/repaid.
B45: • Nestlé runs a structurally negative Cash Conversion Cycle (-19 to -24 days in most years) — suppliers effectively fund working capital, a hallmark of strong bargaining power.
